mycli/AUTHORS
mycli/SPONSORS
mycli/__init__.py
mycli/clibuffer.py
mycli/clistyle.py
mycli/clitoolbar.py
mycli/compat.py
mycli/completion_refresher.py
mycli/config.py
mycli/key_bindings.py
mycli/lexer.py
mycli/magic.py
mycli/main.py
mycli/myclirc
mycli/sqlcompleter.py
mycli/sqlexecute.py
mycli/packages/__init__.py
mycli/packages/completion_engine.py
mycli/packages/filepaths.py
mycli/packages/hybrid_redirection.py
mycli/packages/parseutils.py
mycli/packages/prompt_utils.py
mycli/packages/shortcuts.py
mycli/packages/sqlresult.py
mycli/packages/paramiko_stub/__init__.py
mycli/packages/special/__init__.py
mycli/packages/special/dbcommands.py
mycli/packages/special/delimitercommand.py
mycli/packages/special/favoritequeries.py
mycli/packages/special/iocommands.py
mycli/packages/special/llm.py
mycli/packages/special/main.py
mycli/packages/special/utils.py
mycli/packages/tabular_output/__init__.py
mycli/packages/tabular_output/sql_format.py
mycli/packages/toolkit/__init__.py
mycli/packages/toolkit/fzf.py
mycli/packages/toolkit/history.py
mycli-1.44.2.dist-info/licenses/AUTHORS.rst
mycli-1.44.2.dist-info/licenses/LICENSE.txt
mycli-1.44.2.dist-info/METADATA
mycli-1.44.2.dist-info/WHEEL
mycli-1.44.2.dist-info/entry_points.txt
mycli-1.44.2.dist-info/top_level.txt
mycli-1.44.2.dist-info/RECORD
