Metadata-Version: 2.4
Name: mycli
Version: 1.44.2
Summary: CLI for MySQL Database. With auto-completion and syntax highlighting.
Author-email: Mycli Core Team <mycli-dev@googlegroups.com>
License-Expression: BSD-3-Clause
Project-URL: homepage, http://mycli.net
Requires-Python: >=3.10
License-File: LICENSE.txt
License-File: AUTHORS.rst
Requires-Dist: click>=8.3.1
Requires-Dist: cryptography>=1.0.0
Requires-Dist: Pygments>=1.6
Requires-Dist: prompt_toolkit<4.0.0,>=3.0.6
Requires-Dist: PyMySQL>=0.9.2
Requires-Dist: sqlparse<0.6.0,>=0.3.0
Requires-Dist: sqlglot[rs]==27.*
Requires-Dist: configobj>=5.0.5
Requires-Dist: cli_helpers[styles]>=2.7.0
Requires-Dist: pyperclip>=1.8.1
Requires-Dist: pycryptodomex
Requires-Dist: pyfzf>=0.3.1
Provides-Extra: ssh
Requires-Dist: paramiko; extra == "ssh"
Requires-Dist: sshtunnel; extra == "ssh"
Provides-Extra: llm
Requires-Dist: llm>=0.19.0; extra == "llm"
Requires-Dist: setuptools; extra == "llm"
Requires-Dist: pip; extra == "llm"
Provides-Extra: all
Requires-Dist: mycli[ssh]; extra == "all"
Requires-Dist: mycli[llm]; extra == "all"
Provides-Extra: dev
Requires-Dist: behave>=1.2.6; extra == "dev"
Requires-Dist: coverage>=7.2.7; extra == "dev"
Requires-Dist: mypy~=1.18.1; extra == "dev"
Requires-Dist: pexpect>=4.9.0; extra == "dev"
Requires-Dist: pytest>=7.4.4; extra == "dev"
Requires-Dist: pytest-cov>=4.1.0; extra == "dev"
Requires-Dist: tox>=4.8.0; extra == "dev"
Requires-Dist: pdbpp>=0.10.3; extra == "dev"
Requires-Dist: paramiko; extra == "dev"
Requires-Dist: sshtunnel; extra == "dev"
Requires-Dist: llm>=0.19.0; extra == "dev"
Requires-Dist: setuptools; extra == "dev"
Requires-Dist: pip; extra == "dev"
Requires-Dist: ruff~=0.14.10; extra == "dev"
Dynamic: license-file
